{"type":"Topology","arcs":[],"objects":{"malaysia_all_state":{"type":"GeometryCollection","geometries":[{"type":null,"properties":{"id":"254073383","lat":"6.4307281","long":"100.2718795","name":"Arau","isIn":"Perlis"}},{"type":null,"properties":{"id":"986041799","lat":"6.6598773","long":"100.3164554","name":"Padang Besar","isIn":"Perlis"}},{"type":null,"properties":{"id":"2610748548","lat":"6.4389312","long":"100.1944838","name":"Kangar","isIn":"Perlis"}},{"type":null,"properties":{"id":"254072842","lat":"5.5126654","long":"100.554626","name":"Padang Serai","isIn":"Kedah"}},{"type":null,"properties":{"id":"3290145603","lat":"6.2139888","long":"100.2658606","name":"Jerlun","isIn":"Kedah"}},{"type":null,"properties":{"id":"254074254","lat":"5.2861845","long":"100.6272266","name":"Terap","isIn":"Kedah"}},{"type":null,"properties":{"id":"254073014","lat":"6.1673132","long":"100.5174321","name":"Pokok Sena","isIn":"Kedah"}},{"type":null,"properties":{"id":"295037382","lat":"6.1231908","long":"100.3683962","name":"Alor Setar","isIn":"Kedah"}},{"type":null,"properties":{"id":"254072926","lat":"6.1072177","long":"100.2934899","name":"Kuala Kedah","isIn":"Kedah"}},{"type":null,"properties":{"id":"254073301","lat":"5.8188544","long":"100.7442773","name":"Sik","isIn":"Kedah"}},{"type":null,"properties":{"id":"254073470","lat":"5.7226681","long":"100.4136266","name":"Merbok","isIn":"Kedah"}},{"type":null,"properties":{"id":"254072891","lat":"5.6435195","long":"100.4869513","name":"Sungai Petani","isIn":"Kedah"}},{"type":null,"properties":{"id":"254074209","lat":"5.6774578","long":"100.9172699","name":"Baling","isIn":"Kedah"}},{"type":null,"properties":{"id":"254072842","lat":"5.5126654","long":"100.554626","name":"Padang Serai","isIn":"Kedah"}},{"type":null,"properties":{"id":"648755642","lat":"5.3663769","long":"100.5525705","name":"Kulim","isIn":"Kedah"}},{"type":null,"properties":{"id":"254072921","lat":"6.1983831","long":"102.1681933","name":"Tumpat","isIn":"Kelantan"}},{"type":null,"properties":{"id":"207539450","lat":"6.1256053","long":"102.2393455","name":"Kota Bharu","isIn":"Kelantan"}},{"type":null,"properties":{"id":"369488104","lat":"6.0494592","long":"102.1399444","name":"Pasir Mas","isIn":"Kelantan"}},{"type":null,"properties":{"id":"254073283","lat":"6.0181186","long":"101.9728195","name":"Rantau Panjang","isIn":"Kelantan"}},{"type":null,"properties":{"id":"369488298","lat":"6.0940366","long":"102.2845137","name":"Kubang Kerian","isIn":"Kelantan"}},{"type":null,"properties":{"id":"254073423","lat":"6.0624104","long":"102.3999806","name":"Bachok","isIn":"Kelantan"}},{"type":null,"properties":{"id":"254073075","lat":"5.9588765","long":"102.251282","name":"Ketereh","isIn":"Kelantan"}},{"type":null,"properties":{"id":"369488884","lat":"5.8097754","long":"102.1484103","name":"Tanah Merah","isIn":"Kelantan"}},{"type":null,"properties":{"id":"369488722","lat":"5.8355343","long":"102.4050452","name":"Pasir Puteh","isIn":"Kelantan"}},{"type":null,"properties":{"id":"254074123","lat":"5.7641131","long":"102.214217","name":"Machang","isIn":"Kelantan"}},{"type":null,"properties":{"id":"254072819","lat":"5.6955226","long":"101.8449367","name":"Jeli","isIn":"Kelantan"}},{"type":null,"properties":{"id":"254072948","lat":"5.5300168","long":"102.199106","name":"Kuala Krai","isIn":"Kelantan"}},{"type":null,"properties":{"id":"254074035","lat":"4.8792724","long":"101.9652332","name":"Gua Musang","isIn":"Kelantan"}}]}}}